swagger_plugin_for_sphinx/__init__.py
swagger_plugin_for_sphinx/_plugin.py
swagger_plugin_for_sphinx/full_page_template.j2
swagger_plugin_for_sphinx/inline_template.j2
swagger_plugin_for_sphinx/py.typed
swagger_plugin_for_sphinx-6.0.0.dist-info/licenses/LICENSE
swagger_plugin_for_sphinx-6.0.0.dist-info/METADATA
swagger_plugin_for_sphinx-6.0.0.dist-info/WHEEL
swagger_plugin_for_sphinx-6.0.0.dist-info/top_level.txt
swagger_plugin_for_sphinx-6.0.0.dist-info/RECORD
